standard_packages/__init__.py
standard_packages/core.py
standard_packages/log.py
standard_packages/server.py
standard_packages-0.1.2.dist-info/METADATA
standard_packages-0.1.2.dist-info/WHEEL
standard_packages-0.1.2.dist-info/top_level.txt
standard_packages-0.1.2.dist-info/RECORD
