Metadata-Version: 2.4
Name: standard-packages
Version: 0.1.2
Summary: Add your description here
Requires-Python: >=3.13
Requires-Dist: fastapi>=0.116.1
Requires-Dist: pydantic>=2.11.7
Requires-Dist: pytest>=8.4.1
Requires-Dist: toml==0.10.2
Requires-Dist: uvicorn>=0.35.0
